alice/__init__.py
alice/__main__.py
alice_in_shell-0.1.19.dist-info/entry_points.txt
alice_in_shell-0.1.19.dist-info/LICENSE
alice_in_shell-0.1.19.dist-info/WHEEL
alice_in_shell-0.1.19.dist-info/METADATA
alice_in_shell-0.1.19.dist-info/RECORD
