Metadata-Version: 2.1
Name: alice_in_shell
Version: 0.1.19
Summary: Alice in shell
Home-page: https://github.com/hokkubit/Alice
Author: Denis Aseev
Author-email: brerfox33@gmail.com
Classifier: License :: OSI Approved :: MIT License
